LICENSE.txt
MANIFEST.in
README.rst
setup.py
musette/__init__.py
musette/_environ.py
musette/compat.py
musette/interpolation.py
musette/test.py
musette.egg-info/PKG-INFO
musette.egg-info/SOURCES.txt
musette.egg-info/dependency_links.txt
musette.egg-info/not-zip-safe
musette.egg-info/top_level.txt
musette/data/common.properties
musette/data/env.properties
musette/data/test_env.txt