Metadata-Version: 1.1
Name: musette
Version: 0.5.10
Summary: os.environ proxy based on django-environ
Home-page: http://github.com/averagehuman/musette
Author: gmflanagan
Author-email: gmflanagan@outlook.com
License: MIT License
Keywords: d,j,a,n,g,o, ,e,n,v,i,r,o,n,m,e,n,t, ,v,a,r,i,a,b,l,e,s, ,1,2,f,a,c,t,o,r, ,o,s,.,e,n,v,i,r,o,n
Platform: UNKNOWN
Classifier: Development Status :: 3 - Alpha
Classifier: Intended Audience :: Information Technology
Classifier: Programming Language :: Python
Classifier: Programming Language :: Python :: 2
Classifier: Programming Language :: Python :: 3
Classifier: Topic :: Software Development :: Libraries :: Python Modules
Classifier: Topic :: Utilities
Classifier: License :: OSI Approved :: MIT License
Classifier: Framework :: Django
